EXPANSE/ResolvedGalaxy.py
EXPANSE/__init__.py
EXPANSE/_version.py
EXPANSE/utils.py
EXPANSE/bagpipes/__init__.py
EXPANSE/bagpipes/pipes_models.py
EXPANSE/bagpipes/plotpipes.py
EXPANSE/bagpipes/run_bagpipes_parallel.py
EXPANSE/bagpipes/filters/F070W.dat
EXPANSE/bagpipes/filters/F090W.dat
EXPANSE/bagpipes/filters/F098M.dat
EXPANSE/bagpipes/filters/F1000W.dat
EXPANSE/bagpipes/filters/F105W.dat
EXPANSE/bagpipes/filters/F110W.dat
EXPANSE/bagpipes/filters/F1130W.dat
EXPANSE/bagpipes/filters/F115W.dat
EXPANSE/bagpipes/filters/F125W.dat
EXPANSE/bagpipes/filters/F126N.dat
EXPANSE/bagpipes/filters/F127M.dat
EXPANSE/bagpipes/filters/F1280W.dat
EXPANSE/bagpipes/filters/F128N.dat
EXPANSE/bagpipes/filters/F130N.dat
EXPANSE/bagpipes/filters/F132N.dat
EXPANSE/bagpipes/filters/F139M.dat
EXPANSE/bagpipes/filters/F140W.dat
EXPANSE/bagpipes/filters/F1500W.dat
EXPANSE/bagpipes/filters/F150W.dat
EXPANSE/bagpipes/filters/F153M.dat
EXPANSE/bagpipes/filters/F160W.dat
EXPANSE/bagpipes/filters/F162M.dat
EXPANSE/bagpipes/filters/F164N.dat
EXPANSE/bagpipes/filters/F167N.dat
EXPANSE/bagpipes/filters/F1800W.dat
EXPANSE/bagpipes/filters/F182M.dat
EXPANSE/bagpipes/filters/F200W.dat
EXPANSE/bagpipes/filters/F2100W.dat
EXPANSE/bagpipes/filters/F210M.dat
EXPANSE/bagpipes/filters/F212N.dat
EXPANSE/bagpipes/filters/F250M.dat
EXPANSE/bagpipes/filters/F2550W.dat
EXPANSE/bagpipes/filters/F277W.dat
EXPANSE/bagpipes/filters/F300M.dat
EXPANSE/bagpipes/filters/F323N.dat
EXPANSE/bagpipes/filters/F335M.dat
EXPANSE/bagpipes/filters/F356W.dat
EXPANSE/bagpipes/filters/F360M.dat
EXPANSE/bagpipes/filters/F405N.dat
EXPANSE/bagpipes/filters/F410M.dat
EXPANSE/bagpipes/filters/F430M.dat
EXPANSE/bagpipes/filters/F435W.dat
EXPANSE/bagpipes/filters/F444W.dat
EXPANSE/bagpipes/filters/F460M.dat
EXPANSE/bagpipes/filters/F466N.dat
EXPANSE/bagpipes/filters/F470N.dat
EXPANSE/bagpipes/filters/F475W.dat
EXPANSE/bagpipes/filters/F480M.dat
EXPANSE/bagpipes/filters/F550M.dat
EXPANSE/bagpipes/filters/F555W.dat
astro_expanse-0.1.6.dev0.dist-info/licenses/LICENSE.md
astro_expanse-0.1.6.dev0.dist-info/METADATA
astro_expanse-0.1.6.dev0.dist-info/WHEEL
astro_expanse-0.1.6.dev0.dist-info/entry_points.txt
astro_expanse-0.1.6.dev0.dist-info/top_level.txt
astro_expanse-0.1.6.dev0.dist-info/RECORD
