Metadata-Version: 2.4
Name: astro-expanse
Version: 0.1.6.dev0
Summary: Resolved Galaxy Analysis and Exploration
Author-email: "T. Harvey" <tharvey303@gmail.com>
Maintainer-email: "T. Harvey" <tharvey303@gmail.com>
License:                     GNU GENERAL PUBLIC LICENSE
Project-URL: Source, https://github.com/tHarvey303/EXPANSE
Keywords: galaxy,modelling,smoothed particle hydrodynamics,particles,nbody,galaxy formation,parametric,theory,sph,cosmology,galaxy evolution,survey,space telescope,SED,sed,spectral energy distribution,stellar population,synthesis
Classifier: Development Status :: 4 - Beta
Classifier: Intended Audience :: Science/Research
Classifier: Topic :: Scientific/Engineering :: Astronomy
Classifier: License :: OSI Approved :: GNU General Public License v3 (GPLv3)
Classifier: Programming Language :: Python :: 3.8
Classifier: Programming Language :: Python :: 3.9
Classifier: Programming Language :: Python :: 3.10
Classifier: Programming Language :: Python :: 3.11
Classifier: Programming Language :: Python :: 3.12
Classifier: Programming Language :: Python :: 3 :: Only
Requires-Python: >=3.8
License-File: LICENSE.md
Requires-Dist: setuptools
Requires-Dist: astropy
Requires-Dist: h5py
Requires-Dist: numpy>=1.23
Requires-Dist: packaging
Requires-Dist: scipy
Requires-Dist: joblib
Requires-Dist: unyt
Requires-Dist: panel
Requires-Dist: xarray
Requires-Dist: hvplot
Requires-Dist: holoviews
Requires-Dist: cmasher
Requires-Dist: click>=8.1
Requires-Dist: dust_extinction
Requires-Dist: matplotlib
Requires-Dist: spectres
Requires-Dist: bokeh
Requires-Dist: photutils
Requires-Dist: tqdm
Requires-Dist: requests
Requires-Dist: pandas
Requires-Dist: corner
Requires-Dist: regions
Provides-Extra: dev
Requires-Dist: ruff>=0.3.0; extra == "dev"
Requires-Dist: pre-commit; extra == "dev"
Provides-Extra: test
Requires-Dist: nbmake; extra == "test"
Requires-Dist: pre-commit; extra == "test"
Requires-Dist: pytest; extra == "test"
Requires-Dist: ruff>=0.3.0; extra == "test"
Requires-Dist: mypy>=0.910; extra == "test"
Provides-Extra: extend
Requires-Dist: galfind; extra == "extend"
Requires-Dist: astroquery; extra == "extend"
Requires-Dist: opencv-python; extra == "extend"
Requires-Dist: webbpsf; extra == "extend"
Requires-Dist: vorbin; extra == "extend"
Provides-Extra: sed-fitting
Requires-Dist: dense_basis; extra == "sed-fitting"
Requires-Dist: fsps; extra == "sed-fitting"
Requires-Dist: emcee; extra == "sed-fitting"
Requires-Dist: bagpipes; extra == "sed-fitting"
Requires-Dist: statsmodels; extra == "sed-fitting"
Provides-Extra: mock
Requires-Dist: synthesizer; extra == "mock"
Requires-Dist: unyt; extra == "mock"
Provides-Extra: detection
Requires-Dist: sep-pjw; extra == "detection"
Provides-Extra: viewer
Requires-Dist: panel; extra == "viewer"
Requires-Dist: holoviews; extra == "viewer"
Requires-Dist: xarray; extra == "viewer"
Requires-Dist: hvplot; extra == "viewer"
Requires-Dist: plotly; extra == "viewer"
Provides-Extra: morphology
Requires-Dist: pysersic; extra == "morphology"
Requires-Dist: pyautogalaxy; extra == "morphology"
Requires-Dist: pygalfitm; extra == "morphology"
Dynamic: license-file
